COPYING
MANIFEST.in
README
health_genetics_view.xml
setup.py
./__init__.py
./health_genetics.py
./health_genetics_view.xml
./tryton.cfg
./data/disease_genes.xml
./doc/index.rst
./icons/dna.svg
./locale/ar.po
./locale/de.po
./locale/el.po
./locale/es.po
./locale/fr.po
./locale/it_IT.po
./locale/ja_JP.po
./locale/lo.po
./locale/pt_BR.po
./locale/zh_CN.po
./security/access_rights.xml
./tests/__init__.py
./tests/test_health_genetics.py
./view/gnuhealth_disease_gene.xml
./view/gnuhealth_disease_gene_tree.xml
./view/gnuhealth_family_diseases.xml
./view/gnuhealth_family_diseases_tree.xml
./view/gnuhealth_gene_variant.xml
./view/gnuhealth_gene_variant_phenotype.xml
./view/gnuhealth_gene_variant_phenotype_tree.xml
./view/gnuhealth_gene_variant_tree.xml
./view/gnuhealth_genetic_risk.xml
./view/gnuhealth_genetic_risk_tree.xml
./view/gnuhealth_patient.xml
./view/gnuhealth_protein_disease.xml
./view/gnuhealth_protein_disease_tree.xml
data/disease_genes.xml
doc/index.rst
icons/README
icons/dna.svg
locale/ar.po
locale/de.po
locale/el.po
locale/es.po
locale/fr.po
locale/it_IT.po
locale/ja_JP.po
locale/lo.po
locale/pt_BR.po
locale/zh_CN.po
security/access_rights.xml
trytond_health_genetics.egg-info/PKG-INFO
trytond_health_genetics.egg-info/SOURCES.txt
trytond_health_genetics.egg-info/dependency_links.txt
trytond_health_genetics.egg-info/entry_points.txt
trytond_health_genetics.egg-info/not-zip-safe
trytond_health_genetics.egg-info/requires.txt
trytond_health_genetics.egg-info/top_level.txt
view/gnuhealth_disease_gene.xml
view/gnuhealth_disease_gene_tree.xml
view/gnuhealth_family_diseases.xml
view/gnuhealth_family_diseases_tree.xml
view/gnuhealth_gene_variant.xml
view/gnuhealth_gene_variant_phenotype.xml
view/gnuhealth_gene_variant_phenotype_tree.xml
view/gnuhealth_gene_variant_tree.xml
view/gnuhealth_genetic_risk.xml
view/gnuhealth_genetic_risk_tree.xml
view/gnuhealth_patient.xml
view/gnuhealth_protein_disease.xml
view/gnuhealth_protein_disease_tree.xml